geometron/__init__.py
geometron/core.py
geometron/geometries/__init__.py
geometron/geometries/angles.py
geometron/geometries/conversions.py
geometron/geometries/cubic_length.py
geometron/geometries/transforms.py
geometron/geometries/vectors.py
geometron/interpolation/__init__.py
geometron/interpolation/interpolation_2d.py
geometron/plot/__init__.py
geometron/plot/basemaps.py
geometron/plot/geological_maps.py
geometron/plot/geometries.py
geometron/plot/symbols.py
geometron/plot/vectors.py
geometron/plot/svg_symbols/geophone.svg
geometron/plot/svg_symbols/landmark.svg
geometron/plot/svg_symbols/shot.svg
geometron/plot/svg_symbols/stake.svg
geometron/plot/svg_symbols/station.svg
geometron/survey/__init__.py
geometron/survey/survey.py
geometron/utils/__init__.py
geometron/utils/geoservices.py
geometron/utils/io.py
geometron/utils/str.py
geometron/utils/url.py
geometron/vtk/__init__.py
geometron/vtk/gdf_to_vtk.py
geometron/vtk/image_to_vtk.py
geometron/vtk/transforms.py
geometron-0.1.14.dist-info/AUTHORS
geometron-0.1.14.dist-info/LICENSE
geometron-0.1.14.dist-info/METADATA
geometron-0.1.14.dist-info/WHEEL
geometron-0.1.14.dist-info/pbr.json
geometron-0.1.14.dist-info/top_level.txt
geometron-0.1.14.dist-info/RECORD
