Metadata-Version: 2.1
Name: geometron
Version: 0.1.14
Summary: Tools for operations on geometrical objects
Author-email: "O. Kaufmann" <olivier.kaufmann@umons.ac.be>
Maintainer: All the contributors
License: GPLv3.0
Classifier: Programming Language :: Python :: 3
Classifier: Operating System :: OS Independent
Requires-Python: >=3.8
License-File: LICENSE
License-File: AUTHORS
Requires-Dist: matplotlib>2.2.0
Requires-Dist: numpy<2.0.0,>=1.26.1
Requires-Dist: pandas
Requires-Dist: geopandas
Requires-Dist: scipy
Requires-Dist: shapely
Requires-Dist: pyvista
Requires-Dist: descartes
Requires-Dist: pillow
Requires-Dist: requests
Requires-Dist: pyparsing<3
Requires-Dist: rasterio
Requires-Dist: svgpath2mpl
Requires-Dist: svgpathtools
Requires-Dist: rasterio
Requires-Dist: svgpath2mpl
